LICENSE.txt
README.md
llmkey.desktop
llmkey.svg
setup.py
llmkey/__init__.py
llmkey/__main__.py
llmkey/bus.py
llmkey/config.py
llmkey/credentials.py
llmkey/errors.py
llmkey/gui_first_run.py
llmkey/gui_menu.py
llmkey/gui_prompt.py
llmkey/gui_reply.py
llmkey/gui_settings.py
llmkey/gui_status.py
llmkey/gui_tray.py
llmkey/gui_welcome.py
llmkey/hotkeys.py
llmkey/icon.ico
llmkey/llm.py
llmkey/models_gui.py
llmkey/runner.py
llmkey/serve.py
llmkey/tk_tools.py
llmkey.egg-info/PKG-INFO
llmkey.egg-info/SOURCES.txt
llmkey.egg-info/dependency_links.txt
llmkey.egg-info/entry_points.txt
llmkey.egg-info/requires.txt
llmkey.egg-info/top_level.txt