Metadata-Version: 2.1
Name: llmkey
Version: 7.2
Home-page: https://github.com/talwrii/llmkey
Author: Read with ai
Author-email: readwithai@gmail.com
License: MIT
Keywords: LLM,GPT,clipboard
License-File: LICENSE.txt
